__init__.py
icsr/__init__.py
icsr/evidence.py
icsr/helpers.py
icsr/metrics.py
icsr/structure.py
icsr/utils.py
icsr-0.0.12.dist-info/LICENSE
icsr-0.0.12.dist-info/METADATA
icsr-0.0.12.dist-info/WHEEL
icsr-0.0.12.dist-info/top_level.txt
icsr-0.0.12.dist-info/RECORD
