Metadata-Version: 2.1
Name: icsr
Version: 0.0.12
Summary: Metrics for ICSR prediction.
Author-email: Karel D'Oosterlinck <kareldoosterlinck@gmail.com>
Project-URL: Homepage, https://github.com/KarelDO/icsr-metrics
Project-URL: Bug Tracker, https://github.com/KarelDO/icsr-metrics/issues
Classifier: Programming Language :: Python :: 3
Classifier: License :: OSI Approved :: MIT License
Classifier: Operating System :: OS Independent
Requires-Python: >=3.9
License-File: LICENSE
Requires-Dist: numpy (>=1.24.1)
Requires-Dist: pydantic (>=1.10.4)
Requires-Dist: scipy (>=1.10.0)
